download_giab/__init__.py
download_giab/entry.py
download_giab-0.7.0.dist-info/LICENSE
download_giab-0.7.0.dist-info/METADATA
download_giab-0.7.0.dist-info/WHEEL
download_giab-0.7.0.dist-info/entry_points.txt
download_giab-0.7.0.dist-info/top_level.txt
download_giab-0.7.0.dist-info/RECORD
