Metadata-Version: 2.1
Name: download-giab
Version: 0.7.0
Summary: Utility Python package to download Genome-in-a-Bottle data from their index files.
Home-page: https://github.com/davidlougheed/download_giab
Author: David Lougheed
Author-email: david.lougheed@gmail.com
License: GPLv3
Platform: UNKNOWN
Classifier: Programming Language :: Python :: 3 :: Only
Classifier: License :: OSI Approved :: GNU General Public License v3 (GPLv3)
Classifier: Operating System :: OS Independent
Requires-Python: ~=3.6
License-File: LICENSE
Requires-Dist: requests (<3,>=2.20)
